cloudscale_cli/__init__.py
cloudscale_cli/cli.py
cloudscale_cli/interface_parameter_parser.py
cloudscale_cli/spinner.py
cloudscale_cli/util.py
cloudscale_cli/version.py
cloudscale_cli/commands/__init__.py
cloudscale_cli/commands/custom_image.py
cloudscale_cli/commands/flavor.py
cloudscale_cli/commands/floating_ip.py
cloudscale_cli/commands/image.py
cloudscale_cli/commands/network.py
cloudscale_cli/commands/objects_user.py
cloudscale_cli/commands/region.py
cloudscale_cli/commands/server.py
cloudscale_cli/commands/server_group.py
cloudscale_cli/commands/subnet.py
cloudscale_cli/commands/volume.py
cloudscale_cli-1.5.0.dist-info/licenses/LICENSE
cloudscale_cli-1.5.0.dist-info/METADATA
cloudscale_cli-1.5.0.dist-info/WHEEL
cloudscale_cli-1.5.0.dist-info/entry_points.txt
cloudscale_cli-1.5.0.dist-info/top_level.txt
cloudscale_cli-1.5.0.dist-info/RECORD
