Metadata-Version: 2.4
Name: cloudscale-cli
Version: 1.5.0
Summary: Command line interface client for cloudscale.ch
Home-page: https://github.com/cloudscale-ch/cloudscale-cli
Author: René Moser
Author-email: mail@renemoser.net
License: MIT
Classifier: Intended Audience :: System Administrators
Classifier: Development Status :: 5 - Production/Stable
Classifier: Programming Language :: Python :: 3
Classifier: License :: OSI Approved :: MIT License
Classifier: Operating System :: OS Independent
Classifier: Environment :: Console
Requires-Python: >=3.6
License-File: LICENSE
Requires-Dist: cloudscale-sdk>=0.6.2
Requires-Dist: click>=7.0.0
Requires-Dist: tabulate
Requires-Dist: pygments
Requires-Dist: jmespath
Requires-Dist: yaspin
Requires-Dist: natsort
Provides-Extra: highlight
Requires-Dist: pygments; extra == "highlight"
Dynamic: author
Dynamic: author-email
Dynamic: classifier
Dynamic: description
Dynamic: description-content-type
Dynamic: home-page
Dynamic: license
Dynamic: license-file
Dynamic: provides-extra
Dynamic: requires-dist
Dynamic: requires-python
Dynamic: summary
